stankeviciuscalculator.py
stankeviciuscalculator-0.3.dist-info/WHEEL
stankeviciuscalculator-0.3.dist-info/METADATA
stankeviciuscalculator-0.3.dist-info/RECORD
