Metadata-Version: 2.1
Name: stankeviciuscalculator
Version: 0.3
Summary: Calculator module. 
Author: Tomas Stankevicius
Classifier: License :: OSI Approved :: MIT License
